alt_error_handling/__init__.py
alt_error_handling/constants.py
alt_error_handling/core.py
alt_error_handling/py.typed
alt_error_handling-0.1.0.dist-info/licenses/LICENSE
alt_error_handling-0.1.0.dist-info/METADATA
alt_error_handling-0.1.0.dist-info/WHEEL
alt_error_handling-0.1.0.dist-info/top_level.txt
alt_error_handling-0.1.0.dist-info/RECORD
